utils/__init__.py
utils/generate_latex_image.py
utils/generate_latex_table.py
hse_advanced_python_hw2_maksimkash-0.0.1.dist-info/METADATA
hse_advanced_python_hw2_maksimkash-0.0.1.dist-info/WHEEL
hse_advanced_python_hw2_maksimkash-0.0.1.dist-info/top_level.txt
hse_advanced_python_hw2_maksimkash-0.0.1.dist-info/RECORD
