Metadata-Version: 2.2
Name: hse_advanced_python_hw2_maksimkaSh
Version: 0.0.1
Summary: Latex library
Author: Maksim Shtein
Author-email: shteinmaks@gmail.com
Classifier: Programming Language :: Python :: 3
Classifier: License :: OSI Approved :: MIT License
Classifier: Operating System :: OS Independent
Requires-Python: >=3.6
Dynamic: author
Dynamic: author-email
Dynamic: classifier
Dynamic: requires-python
Dynamic: summary
